vlgi_datasets/__init__.py
vlgi_datasets/open_pyxl_dataset.py
vlgi_datasets/partitioned_sharepoint_dataset.py
vlgi_datasets/pdf_dataset.py
vlgi_datasets/postgres_soft_replace_dataset.py
vlgi_datasets/postgres_upsert_table.py
vlgi_datasets/sharepoint_excel_dataset.py
vlgi_datasets-0.4.2.dist-info/METADATA
vlgi_datasets-0.4.2.dist-info/WHEEL
vlgi_datasets-0.4.2.dist-info/top_level.txt
vlgi_datasets-0.4.2.dist-info/RECORD
