Metadata-Version: 2.4
Name: vlgi-datasets
Version: 0.4.2
Summary: A package with custom kedro datasets for VLGI
Author-email: Tecnologia Grupo Sozo <tecnologia@gruposozo.com.br>
Classifier: Programming Language :: Python :: 3
Classifier: License :: OSI Approved :: MIT License
Classifier: Operating System :: OS Independent
Requires-Python: >=3.6
Requires-Dist: pandas>=1.5.3
Requires-Dist: kedro<=0.18.14,>=0.18.2
Requires-Dist: SQLAlchemy<=2.0.0,>=1.4.39
Requires-Dist: Office365-REST-Python-Client~=2.3.16
